param_parser/__init__.py
param_parser/exception.py
param_parser/lexer.py
param_parser/node.py
param_parser/parser.py
param_parser/token.py
param_parser-1.1.0.dist-info/LICENSE
param_parser-1.1.0.dist-info/METADATA
param_parser-1.1.0.dist-info/WHEEL
param_parser-1.1.0.dist-info/top_level.txt
param_parser-1.1.0.dist-info/RECORD
